divide/__init__.py
divide/by_three.py
multiply/__init__.py
multiply/by_three.py
NIVESH_6-2.1.6.dist-info/LICENSE.txt
NIVESH_6-2.1.6.dist-info/METADATA
NIVESH_6-2.1.6.dist-info/WHEEL
NIVESH_6-2.1.6.dist-info/top_level.txt
NIVESH_6-2.1.6.dist-info/RECORD
