Metadata-Version: 2.1
Name: NIVESH-6
Version: 2.1.6
Summary: A simple example to understand the basics of developing your first Python package.
Home-page: https://github.com/jacane/pyniv
Author: NIVESH CHAND
Author-email: nivpy@gmail.com
Classifier: Programming Language :: Python :: 3
Classifier: License :: OSI Approved :: MIT License
Classifier: Operating System :: OS Independent
Requires-Python: >=3.6
License-File: LICENSE.txt
